switchboardpy/__init__.py
switchboardpy/aggregator.py
switchboardpy/common.py
switchboardpy/compiled.py
switchboardpy/crank.py
switchboardpy/generated/__init__.py
switchboardpy/generated/accounts/__init__.py
switchboardpy/generated/accounts/aggregator_account_data.py
switchboardpy/generated/accounts/crank_account_data.py
switchboardpy/generated/accounts/job_account_data.py
switchboardpy/generated/accounts/lease_account_data.py
switchboardpy/generated/accounts/oracle_account_data.py
switchboardpy/generated/accounts/oracle_queue_account_data.py
switchboardpy/generated/accounts/permission_account_data.py
switchboardpy/generated/accounts/sb_state.py
switchboardpy/generated/accounts/vrf_account_data.py
switchboardpy/generated/errors/__init__.py
switchboardpy/generated/errors/anchor.py
switchboardpy/generated/errors/custom.py
switchboardpy/generated/instructions/__init__.py
switchboardpy/generated/instructions/aggregator_add_job.py
switchboardpy/generated/instructions/aggregator_init.py
switchboardpy/generated/instructions/aggregator_lock.py
switchboardpy/generated/instructions/aggregator_open_round.py
switchboardpy/generated/instructions/aggregator_remove_job.py
switchboardpy/generated/instructions/aggregator_save_result.py
switchboardpy/generated/instructions/aggregator_set_authority.py
switchboardpy/generated/instructions/aggregator_set_batch_size.py
switchboardpy/generated/instructions/aggregator_set_history_buffer.py
switchboardpy/generated/instructions/aggregator_set_min_jobs.py
switchboardpy/generated/instructions/aggregator_set_min_oracles.py
switchboardpy/generated/instructions/aggregator_set_queue.py
switchboardpy/generated/instructions/aggregator_set_update_interval.py
switchboardpy/generated/instructions/aggregator_set_variance_threshold.py
switchboardpy/generated/instructions/crank_init.py
switchboardpy/generated/instructions/crank_pop.py
switchboardpy/generated/instructions/crank_push.py
switchboardpy/generated/instructions/job_init.py
switchboardpy-0.0.8.dist-info/LICENSE
switchboardpy-0.0.8.dist-info/WHEEL
switchboardpy-0.0.8.dist-info/METADATA
switchboardpy-0.0.8.dist-info/RECORD
