Metadata-Version: 2.1
Name: switchboardpy
Version: 0.0.8
Summary: Switchboard V2 API
Home-page: https://docs.switchboard.xyz
License: MIT
Author: Albert Hermida
Author-email: albert@switchboard.xyz
Requires-Python: >=3.9,<4.0
Classifier: License :: OSI Approved :: MIT License
Classifier: Programming Language :: Python :: 3
Classifier: Programming Language :: Python :: 3.10
Classifier: Programming Language :: Python :: 3.9
Requires-Dist: OSlash (==0.6.3)
Requires-Dist: PyNaCl (==1.4.0)
Requires-Dist: anchorpy (>=0.9.2,<0.10.0)
Requires-Dist: anyio (==3.4.0)
Requires-Dist: apischema (==0.16.6)
Requires-Dist: attrs (==21.2.0)
Requires-Dist: base58 (==2.1.1)
Requires-Dist: borsh-construct (==0.1.0)
Requires-Dist: cachetools (==4.2.4)
Requires-Dist: certifi (==2021.10.8)
Requires-Dist: cffi (==1.15.0)
Requires-Dist: charset-normalizer (==2.0.9)
Requires-Dist: construct (==2.10.67)
Requires-Dist: construct-typing (==0.5.2)
Requires-Dist: h11 (==0.12.0)
Requires-Dist: httpcore (==0.13.7)
Requires-Dist: httpx (==0.18.2)
Requires-Dist: idna (==3.3)
Requires-Dist: inflection (==0.5.1)
Requires-Dist: iniconfig (==1.1.1)
Requires-Dist: jsonrpcclient (>=4.0.2)
Requires-Dist: jsonrpcserver (>=5.0.7)
Requires-Dist: jsonschema (==3.2.0)
Requires-Dist: more-itertools (==8.12.0)
Requires-Dist: packaging (==21.3)
Requires-Dist: pluggy (==1.0.0)
Requires-Dist: protobuf (>=3.5.0.post1)
Requires-Dist: psutil (==5.8.0)
Requires-Dist: py (==1.11.0)
Requires-Dist: pycparser (==2.21)
Requires-Dist: pyparsing (==3.0.6)
Requires-Dist: pyrsistent (==0.18.0)
Requires-Dist: pytest-xprocess (==0.18.1)
Requires-Dist: requests (==2.26.0)
Requires-Dist: rfc3986 (==1.5.0)
Requires-Dist: six (==1.16.0)
Requires-Dist: sniffio (==1.2.0)
Requires-Dist: solana (>0.23.1)
Requires-Dist: sumtypes (==0.1a6)
Requires-Dist: toml (==0.10.2)
Requires-Dist: toolz (==0.11.2)
Requires-Dist: typer (>=0.4.1,<0.5.0)
Requires-Dist: types-cachetools (==4.2.6)
Requires-Dist: typing-extensions (==3.10.0.2)
Requires-Dist: urllib3 (==1.26.7)
Requires-Dist: websockets (==10.1)
Requires-Dist: zstandard (>=0.17.0)
Project-URL: Repository, https://github.com/switchboard-xyz/switchboard-v2/tree/main/libraries/py
